appimage_installer/__init__.py
appimage_installer/locales/de.json
appimage_installer/locales/en.json
appimage_installer/locales/fr.json
appimage_installer/locales/tr.json
appimage_installer-1.0.6.dist-info/licenses/LICENSE
appimage_installer-1.0.6.dist-info/METADATA
appimage_installer-1.0.6.dist-info/WHEEL
appimage_installer-1.0.6.dist-info/entry_points.txt
appimage_installer-1.0.6.dist-info/top_level.txt
appimage_installer-1.0.6.dist-info/RECORD
