Metadata-Version: 2.4
Name: appimage-installer
Version: 1.0.6
Summary: AppImage installer for Linux
Home-page: https://github.com/yourusername/appimage-installer
Author: Your Name
Author-email: Altay Kirecci <altay.kirecci@gmail.com>
License: MIT
Classifier: Programming Language :: Python :: 3
Classifier: Operating System :: POSIX :: Linux
Requires-Python: >=3.6
License-File: LICENSE
Requires-Dist: setuptools>=42
Dynamic: author
Dynamic: home-page
Dynamic: license-file
Dynamic: requires-python
